{"components_autocomplete_index.md":"I--Gy4Vq","components_button_index.md":"CxRQ39qV","components_card_index.md":"BXs11aij","components_checkbox_index.md":"Bq5wHO08","components_datepicker_index.md":"CkEM6E00","components_filter_index.md":"CLEdy51I","components_navigator_index.md":"Bp8fy_0v","components_overlay_index.md":"Ch7Vb4CC","components_scrolliframe_index.md":"BHRjhMtJ","components_select_selectmany.md":"Bdv73WaS","components_table_index.md":"CujlOXVm","components_textfield_index.md":"CJ4CUMTo","components_textfield_sendvariables.md":"D7lp4rAI","components_tiptapeditor_index.md":"BwPRkD1q","index.md":"B4czpOTQ"}
